[
    {
        "date": "7/24",
        "item": "Super KNIGHT Fighting Plakat Male",
        "seller": "Bettaakapes",
        "highBidder": "None",
        "bPrice": "---",
        "reserveMet": "No Bids"
    },
    {
        "date": "7/24",
        "item": "++ Super KNIGHT Fighting Plakat Male ++",
        "seller": "Bettaakapes",
        "highBidder": "None",
        "bPrice": "---",
        "reserveMet": "No Bids"
    },
    {
        "date": "7/24",
        "item": "Super KNIGHT Fighting Plakat Female",
        "seller": "Bettaakapes",
        "highBidder": "None",
        "bPrice": "---",
        "reserveMet": "No Bids"
    },
    {
        "date": "7/30",
        "item": "TOP Plakat #P-201 ship USA CANADA EUROPE",
        "seller": "Ppro",
        "highBidder": "None",
        "bPrice": "---",
        "reserveMet": "No Bids"
    },
    {
        "date": "7/30",
        "item": "TOP Plakat #P-202 ship USA CANADA EUROPE",
        "seller": "Ppro",
        "highBidder": "None",
        "bPrice": "---",
        "reserveMet": "No Bids"
    },
    {
        "date": "7/31",
        "item": "Plakat Red Dragon Full Mask",
        "seller": "Felixbettabenedict",
        "highBidder": "None",
        "bPrice": "---",
        "reserveMet": "No Bids"
    },
    {
        "date": "7/31",
        "item": "Plakat giant Red koi full block",
        "seller": "Felixbettabenedict",
        "highBidder": "None",
        "bPrice": "---",
        "reserveMet": "No Bids"
    },
    {
        "date": "8/1",
        "item": "MaMa !! ++ Giant Plakat Female ++",
        "seller": "Bettaakapes",
        "highBidder": "None",
        "bPrice": "---",
        "reserveMet": "No Bids"
    },
    {
        "date": "8/1",
        "item": "LIGHT !! ++ Giant Plakat Female ++",
        "seller": "Bettaakapes",
        "highBidder": "None",
        "bPrice": "---",
        "reserveMet": "No Bids"
    },
    {
        "date": "8/1",
        "item": "Super Fight ! ++ Giant Plakat Male ++",
        "seller": "Bettaakapes",
        "highBidder": "None",
        "bPrice": "---",
        "reserveMet": "No Bids"
    },
    {
        "date": "8/1",
        "item": "Super Giant Plakat !! ++ Giant Male ++",
        "seller": "Bettaakapes",
        "highBidder": "None",
        "bPrice": "---",
        "reserveMet": "No Bids"
    },
    {
        "date": "8/1",
        "item": "Super Knight Figther Plakat Male",
        "seller": "Bettaakapes",
        "highBidder": "None",
        "bPrice": "---",
        "reserveMet": "No Bids"
    },
    {
        "date": "8/1",
        "item": "Knight Figting Plakat Male",
        "seller": "Bettaakapes",
        "highBidder": "None",
        "bPrice": "---",
        "reserveMet": "No Bids"
    },
    {
        "date": "8/2",
        "item": "Plakat fancy male",
        "seller": "Grimiss",
        "highBidder": "None",
        "bPrice": "---",
        "reserveMet": "No Bids"
    },
    {
        "date": "8/2",
        "item": "Dumbo ear",
        "seller": "Grimiss",
        "highBidder": "None",
        "bPrice": "---",
        "reserveMet": "No Bids"
    },
    {
        "date": "8/2",
        "item": "Female red koi full block",
        "seller": "Grimiss",
        "highBidder": "None",
        "bPrice": "---",
        "reserveMet": "No Bids"
    },
    {
        "date": "8/3",
        "item": "Giant Betta for Sale",
        "seller": "Virtus_betta",
        "highBidder": "None",
        "bPrice": "---",
        "reserveMet": "No Bids"
    },
    {
        "date": "8/3",
        "item": "Plakat for Sale",
        "seller": "Virtus_betta",
        "highBidder": "None",
        "bPrice": "---",
        "reserveMet": "No Bids"
    },
    {
        "date": "8/4",
        "item": "ASSTD BAGAN WARRIOR FIGHTER *INDO IMPORT*",
        "seller": "Jay808",
        "highBidder": "None",
        "bPrice": "---",
        "reserveMet": "No Bids"
    },
    {
        "date": "8/11",
        "item": "Plakat FEmale##Ready For Breeding",
        "seller": "Phusit",
        "highBidder": "None",
        "bPrice": "---",
        "reserveMet": "No Bids"
    },
    {
        "date": "8/11",
        "item": "Giant Plakat !! ++ Super Giant Male ++",
        "seller": "Bettaakapes",
        "highBidder": "None",
        "bPrice": "---",
        "reserveMet": "No Bids"
    },
    {
        "date": "8/11",
        "item": "Kinght Plakat Fighting Male +",
        "seller": "Bettaakapes",
        "highBidder": "None",
        "bPrice": "---",
        "reserveMet": "No Bids"
    },
    {
        "date": "8/11",
        "item": "Kinght Plakat Fighting Male ++",
        "seller": "Bettaakapes",
        "highBidder": "None",
        "bPrice": "---",
        "reserveMet": "No Bids"
    },
    {
        "date": "8/13",
        "item": "Big Ear Lavender Male",
        "seller": "Virtus_betta",
        "highBidder": "None",
        "bPrice": "---",
        "reserveMet": "No Bids"
    },
    {
        "date": "8/14",
        "item": "Giant Plakat Female",
        "seller": "Senaiaqu",
        "highBidder": "None",
        "bPrice": "---",
        "reserveMet": "No Bids"
    },
    {
        "date": "8/14",
        "item": "Giant Betta #002",
        "seller": "Virtus_betta",
        "highBidder": "None",
        "bPrice": "---",
        "reserveMet": "No Bids"
    },
    {
        "date": "8/14",
        "item": "Plakat Female",
        "seller": "Senaiaqu",
        "highBidder": "None",
        "bPrice": "---",
        "reserveMet": "No Bids"
    },
    {
        "date": "8/14",
        "item": "Best Super Plakat Thai AI-01.!",
        "seller": "Phuket_plakat",
        "highBidder": "None",
        "bPrice": "---",
        "reserveMet": "No Bids"
    },
    {
        "date": "8/15",
        "item": "********* Thai Plakat #62 *******",
        "seller": "The_heroic2012",
        "highBidder": "None",
        "bPrice": "---",
        "reserveMet": "No Bids"
    },
    {
        "date": "8/16",
        "item": "TOP Plakat Fighter INDO Blood #P-203 Ship USA.",
        "seller": "Ppro",
        "highBidder": "None",
        "bPrice": "---",
        "reserveMet": "No Bids"
    },
    {
        "date": "8/16",
        "item": "TOP Plakat Fighter Malay Blood #P-204 Ship USA.",
        "seller": "Ppro",
        "highBidder": "None",
        "bPrice": "---",
        "reserveMet": "No Bids"
    },
    {
        "date": "8/16",
        "item": "Super Fighter W101 For Sale.",
        "seller": "Superfightingbetta",
        "highBidder": "None",
        "bPrice": "---",
        "reserveMet": "No Bids"
    },
    {
        "date": "8/16",
        "item": "Super Fighter #W102 For Sale.",
        "seller": "Superfightingbetta",
        "highBidder": "None",
        "bPrice": "---",
        "reserveMet": "No Bids"
    },
    {
        "date": "8/17",
        "item": "Giant Betta #003",
        "seller": "Virtus_betta",
        "highBidder": "None",
        "bPrice": "---",
        "reserveMet": "No Bids"
    },
    {
        "date": "8/17",
        "item": "Giant Betta #006 (Juvenile Koi Orange)",
        "seller": "Virtus_betta",
        "highBidder": "None",
        "bPrice": "---",
        "reserveMet": "No Bids"
    },
    {
        "date": "8/17",
        "item": "Single Tail Plakat Size S",
        "seller": "Virtus_betta",
        "highBidder": "None",
        "bPrice": "---",
        "reserveMet": "No Bids"
    },
    {
        "date": "8/17",
        "item": "Plakat Koi Galaxy Full Mask",
        "seller": "Virtus_betta",
        "highBidder": "None",
        "bPrice": "---",
        "reserveMet": "No Bids"
    },
    {
        "date": "8/18",
        "item": "Giant Betta #007",
        "seller": "Virtus_betta",
        "highBidder": "None",
        "bPrice": "---",
        "reserveMet": "No Bids"
    },
    {
        "date": "8/18",
        "item": "AAA Fighting #40",
        "seller": "Bettagold_",
        "highBidder": "None",
        "bPrice": "---",
        "reserveMet": "No Bids"
    },
    {
        "date": "8/18",
        "item": "AAA Fighting # 49",
        "seller": "Bettagold_",
        "highBidder": "None",
        "bPrice": "---",
        "reserveMet": "No Bids"
    },
    {
        "date": "8/18",
        "item": "AAA Fighting # 45",
        "seller": "Bettagold_",
        "highBidder": "None",
        "bPrice": "---",
        "reserveMet": "No Bids"
    },
    {
        "date": "8/18",
        "item": "AAA Fighting # 49",
        "seller": "Bettagold_",
        "highBidder": "None",
        "bPrice": "---",
        "reserveMet": "No Bids"
    },
    {
        "date": "8/18",
        "item": "AAA Fighting # 53",
        "seller": "Bettagold_",
        "highBidder": "None",
        "bPrice": "---",
        "reserveMet": "No Bids"
    },
    {
        "date": "8/19",
        "item": "Giant Betta #004",
        "seller": "Virtus_betta",
        "highBidder": "None",
        "bPrice": "---",
        "reserveMet": "No Bids"
    },
    {
        "date": "8/19",
        "item": "Giant Betta #005",
        "seller": "Virtus_betta",
        "highBidder": "Fishbutt",
        "bPrice": "$17.00",
        "reserveMet": "Yes"
    },
    {
        "date": "8/20",
        "item": "ASSTD BAGAN WARRIOR FIGHTER *INDO IMPORT*",
        "seller": "Jay808",
        "highBidder": "None",
        "bPrice": "---",
        "reserveMet": "No Bids"
    },
    {
        "date": "8/20",
        "item": "PRO !! ++ Giant Plakat Male ++",
        "seller": "Bettaakapes",
        "highBidder": "None",
        "bPrice": "---",
        "reserveMet": "No Bids"
    },
    {
        "date": "8/20",
        "item": "Don't Miss !! ++ Plakat Super Fighting Male ++",
        "seller": "Bettaakapes",
        "highBidder": "None",
        "bPrice": "---",
        "reserveMet": "No Bids"
    },
    {
        "date": "8/21",
        "item": "MYSTERY BOX OF 2 PLAKAT MALES *INDO IMPORT*",
        "seller": "Jay808",
        "highBidder": "None",
        "bPrice": "---",
        "reserveMet": "No Bids"
    },
    {
        "date": "8/24",
        "item": "P8 MEDAN FEMALE",
        "seller": "Cupangadu",
        "highBidder": "Bubbie",
        "bPrice": "$27.00",
        "reserveMet": "Yes"
    },
    {
        "date": "8/24",
        "item": "MD MEDAN FEMALE",
        "seller": "Cupangadu",
        "highBidder": "Bubbie",
        "bPrice": "$27.00",
        "reserveMet": "Yes"
    }
]